Workbook

Sheet Summary
A1: Arora Traders - Supplier Evidence Workbook (PS 4)
A3: Total billed to suppliers, 3 yrs (Rs) | B3: =Supplier_Impact!D38
A4: Total billing gap: billed minus received x price (Rs) | B4: =Supplier_Impact!F38
A5: of which excess over panel-normal shortage (Rs) | B5: =Supplier_Impact!H38
A6: VS12 Nutan Tubes - headline loss (Rs) | B6: =INDEX(Supplier_Impact!L4:L37,MATCH("VS12",Supplier_Impact!A4:A37,0))
A7: VS19 Thakur Steel - headline loss (Rs) | B7: =INDEX(Supplier_Impact!L4:L37,MATCH("VS19",Supplier_Impact!A4:A37,0))
A8: VS03 Tata Steel Service - headline loss (Rs) | B8: =INDEX(Supplier_Impact!L4:L37,MATCH("VS03",Supplier_Impact!A4:A37,0))
A9: Suppliers rated POOR on the scorecard | B9: =COUNTIF(Scorecard!P4:P37,"POOR")
A10: Lowest composite score among the other suppliers | B10: =SMALL(Scorecard!O4:O37,4)
A12: Sheets: Assumptions | Supplier_Impact (rupees) | Scorecard | PO_Facts (every PO, formulas visible) | Returns_Confirmed | Returns_Inferred | Returns_Attributed | Category_Scorecard | Validation | Sensitivity | Data_Quality_Log
A13: Worked example for VS12: filter PO_Facts on supplier_id = VS12 and sum column R (billed - received x price); it equals Supplier_Impact column F.

Sheet Assumptions
A1: Assumptions and inputs
A3: Panel baseline short-delivery % (median supplier) | B3: 0.51119359 | C3: Median of the 34 suppliers' qty-weighted short %. Computed from data, never from the underperformer flag. Used to separate normal tolerance from excess shortage.
A4: Late-delivery carrying cost, % p.a. (memo only) | B4: 0.12 | C4: Assumption (not from the data). Late-delivery cost proxy is NOT part of the headline loss.
A6: Scorecard weights (sum to 100%)
A7: Short delivery % | B7: 0.35
A8: Late delivery (avg days) | B8: 0.25
A9: Rejection % | B9: 0.15
A10: Returns per 1,000 MT | B10: 0.15
A11: Price vs panel (scaled by z-score) | B11: 0.1
A12: Total | B12: =SUM(B7:B11)
A13: Price z-score at which price score reaches 0 | B13: 3
A14: Tier cut-offs: POOR below / WATCH below | B14: 60 | C14: 85
A17: Colour code: blue = input taken from data or model output; black = formula; green = cross-sheet link. Yellow = assumption you may change.
A18: Not used anywhere: years_of_relationship, is_underperformer. Category source of truth: supplier_master.
A19: Inferred-return probabilities come from the Phase 2 model (see Validation). Per-return values are probability x quantity x batch price.
A20: Dataset scale: total billed is ~Rs 1,009 Cr over 3 years, ~37x the Rs 70-85L/month in the problem statement. Reported as found.
A21: Arora's own payment lateness (avg ~7.3 days) is in PO_Facts column M and Supplier_Impact: expect suppliers to raise it.

Sheet Supplier_Impact
A1: Rupee impact per supplier, 3 years (all figures are live formulas over PO_Facts and the returns sheets)
A3: supplier_id | B3: supplier_name | C3: PO count | D3: Billed | E3: Received x price | F3: BILLING GAP (A) | G3: Panel-normal part of gap | H3: EXCESS GAP (A*) | I3: REJECTION LOSS (B) | J3: CONFIRMED RETURNS (C) | K3: INFERRED RETURNS, expected (D) | L3: HEADLINE LOSS = A*+B+C+D | M3: Rank | N3: Inferred range p10 | O3: Inferred range p90 | P3: Arora avg days late paying
A4: VS01 | B4: Jindal Steel & Power | C4: =COUNTIFS(PO_Facts!$C$2:$C$4801,A4) | D4: =SUMIFS(PO_Facts!$K$2:$K$4801,PO_Facts!$C$2:$C$4801,A4) | E4: =SUMIFS(PO_Facts!$Q$2:$Q$4801,PO_Facts!$C$2:$C$4801,A4) | F4: =D4-E4 | G4: =SUMIFS(PO_Facts!$S$2:$S$4801,PO_Facts!$C$2:$C$4801,A4) | H4: =MAX(0,SUMIFS(PO_Facts!$T$2:$T$4801,PO_Facts!$C$2:$C$4801,A4)) | I4: =SUMIFS(PO_Facts!$U$2:$U$4801,PO_Facts!$C$2:$C$4801,A4) | J4: =SUMIFS(Returns_Confirmed!$K$2:$K$241,Returns_Confirmed!$G$2:$G$241,A4) | K4: =SUMIFS(Returns_Inferred!$H$2:$H$4761,Returns_Inferred!$B$2:$B$4761,A4) | L4: =H4+I4+J4+K4 | M4: =RANK(L4,$L$4:$L$37) | N4: 107456 | O4: 1218389 | P4: =AVERAGEIFS(PO_Facts!$M$2:$M$4801,PO_Facts!$C$2:$C$4801,A4)
A5: VS02 | B5: SAIL Distribution | C5: =COUNTIFS(PO_Facts!$C$2:$C$4801,A5) | D5: =SUMIFS(PO_Facts!$K$2:$K$4801,PO_Facts!$C$2:$C$4801,A5) | E5: =SUMIFS(PO_Facts!$Q$2:$Q$4801,PO_Facts!$C$2:$C$4801,A5) | F5: =D5-E5 | G5: =SUMIFS(PO_Facts!$S$2:$S$4801,PO_Facts!$C$2:$C$4801,A5) | H5: =MAX(0,SUMIFS(PO_Facts!$T$2:$T$4801,PO_Facts!$C$2:$C$4801,A5)) | I5: =SUMIFS(PO_Facts!$U$2:$U$4801,PO_Facts!$C$2:$C$4801,A5) | J5: =SUMIFS(Returns_Confirmed!$K$2:$K$241,Returns_Confirmed!$G$2:$G$241,A5) | K5: =SUMIFS(Returns_Inferred!$H$2:$H$4761,Returns_Inferred!$B$2:$B$4761,A5) | L5: =H5+I5+J5+K5 | M5: =RANK(L5,$L$4:$L$37) | N5: 0 | O5: 722960 | P5: =AVERAGEIFS(PO_Facts!$M$2:$M$4801,PO_Facts!$C$2:$C$4801,A5)
A6: VS03 | B6: Tata Steel Service | C6: =COUNTIFS(PO_Facts!$C$2:$C$4801,A6) | D6: =SUMIFS(PO_Facts!$K$2:$K$4801,PO_Facts!$C$2:$C$4801,A6) | E6: =SUMIFS(PO_Facts!$Q$2:$Q$4801,PO_Facts!$C$2:$C$4801,A6) | F6: =D6-E6 | G6: =SUMIFS(PO_Facts!$S$2:$S$4801,PO_Facts!$C$2:$C$4801,A6) | H6: =MAX(0,SUMIFS(PO_Facts!$T$2:$T$4801,PO_Facts!$C$2:$C$4801,A6)) | I6: =SUMIFS(PO_Facts!$U$2:$U$4801,PO_Facts!$C$2:$C$4801,A6) | J6: =SUMIFS(Returns_Confirmed!$K$2:$K$241,Returns_Confirmed!$G$2:$G$241,A6) | K6: =SUMIFS(Returns_Inferred!$H$2:$H$4761,Returns_Inferred!$B$2:$B$4761,A6) | L6: =H6+I6+J6+K6 | M6: =RANK(L6,$L$4:$L$37) | N6: 3114660 | O6: 5966349 | P6: =AVERAGEIFS(PO_Facts!$M$2:$M$4801,PO_Facts!$C$2:$C$4801,A6)
A7: VS04 | B7: Shyam Metalics | C7: =COUNTIFS(PO_Facts!$C$2:$C$4801,A7) | D7: =SUMIFS(PO_Facts!$K$2:$K$4801,PO_Facts!$C$2:$C$4801,A7) | E7: =SUMIFS(PO_Facts!$Q$2:$Q$4801,PO_Facts!$C$2:$C$4801,A7) | F7: =D7-E7 | G7: =SUMIFS(PO_Facts!$S$2:$S$4801,PO_Facts!$C$2:$C$4801,A7) | H7: =MAX(0,SUMIFS(PO_Facts!$T$2:$T$4801,PO_Facts!$C$2:$C$4801,A7)) | I7: =SUMIFS(PO_Facts!$U$2:$U$4801,PO_Facts!$C$2:$C$4801,A7) | J7: =SUMIFS(Returns_Confirmed!$K$2:$K$241,Returns_Confirmed!$G$2:$G$241,A7) | K7: =SUMIFS(Returns_Inferred!$H$2:$H$4761,Returns_Inferred!$B$2:$B$4761,A7) | L7: =H7+I7+J7+K7 | M7: =RANK(L7,$L$4:$L$37) | N7: 0 | O7: 943948 | P7: =AVERAGEIFS(PO_Facts!$M$2:$M$4801,PO_Facts!$C$2:$C$4801,A7)
A8: VS05 | B8: Bhushan Steel | C8: =COUNTIFS(PO_Facts!$C$2:$C$4801,A8) | D8: =SUMIFS(PO_Facts!$K$2:$K$4801,PO_Facts!$C$2:$C$4801,A8) | E8: =SUMIFS(PO_Facts!$Q$2:$Q$4801,PO_Facts!$C$2:$C$4801,A8) | F8: =D8-E8 | G8: =SUMIFS(PO_Facts!$S$2:$S$4801,PO_Facts!$C$2:$C$4801,A8) | H8: =MAX(0,SUMIFS(PO_Facts!$T$2:$T$4801,PO_Facts!$C$2:$C$4801,A8)) | I8: =SUMIFS(PO_Facts!$U$2:$U$4801,PO_Facts!$C$2:$C$4801,A8) | J8: =SUMIFS(Returns_Confirmed!$K$2:$K$241,Returns_Confirmed!$G$2:$G$241,A8) | K8: =SUMIFS(Returns_Inferred!$H$2:$H$4761,Returns_Inferred!$B$2:$B$4761,A8) | L8: =H8+I8+J8+K8 | M8: =RANK(L8,$L$4:$L$37) | N8: 13251 | O8: 1126742 | P8: =AVERAGEIFS(PO_Facts!$M$2:$M$4801,PO_Facts!$C$2:$C$4801,A8)
A9: VS06 | B9: APL Apollo Tubes | C9: =COUNTIFS(PO_Facts!$C$2:$C$4801,A9) | D9: =SUMIFS(PO_Facts!$K$2:$K$4801,PO_Facts!$C$2:$C$4801,A9) | E9: =SUMIFS(PO_Facts!$Q$2:$Q$4801,PO_Facts!$C$2:$C$4801,A9) | F9: =D9-E9 | G9: =SUMIFS(PO_Facts!$S$2:$S$4801,PO_Facts!$C$2:$C$4801,A9) | H9: =MAX(0,SUMIFS(PO_Facts!$T$2:$T$4801,PO_Facts!$C$2:$C$4801,A9)) | I9: =SUMIFS(PO_Facts!$U$2:$U$4801,PO_Facts!$C$2:$C$4801,A9) | J9: =SUMIFS(Returns_Confirmed!$K$2:$K$241,Returns_Confirmed!$G$2:$G$241,A9) | K9: =SUMIFS(Returns_Inferred!$H$2:$H$4761,Returns_Inferred!$B$2:$B$4761,A9) | L9: =H9+I9+J9+K9 | M9: =RANK(L9,$L$4:$L$37) | N9: 53981 | O9: 1212694 | P9: =AVERAGEIFS(PO_Facts!$M$2:$M$4801,PO_Facts!$C$2:$C$4801,A9)
A10: VS07 | B10: Prakash Industries | C10: =COUNTIFS(PO_Facts!$C$2:$C$4801,A10) | D10: =SUMIFS(PO_Facts!$K$2:$K$4801,PO_Facts!$C$2:$C$4801,A10) | E10: =SUMIFS(PO_Facts!$Q$2:$Q$4801,PO_Facts!$C$2:$C$4801,A10) | F10: =D10-E10 | G10: =SUMIFS(PO_Facts!$S$2:$S$4801,PO_Facts!$C$2:$C$4801,A10) | H10: =MAX(0,SUMIFS(PO_Facts!$T$2:$T$4801,PO_Facts!$C$2:$C$4801,A10)) | I10: =SUMIFS(PO_Facts!$U$2:$U$4801,PO_Facts!$C$2:$C$4801,A10) | J10: =SUMIFS(Returns_Confirmed!$K$2:$K$241,Returns_Confirmed!$G$2:$G$241,A10) | K10: =SUMIFS(Returns_Inferred!$H$2:$H$4761,Returns_Inferred!$B$2:$B$4761,A10) | L10: =H10+I10+J10+K10 | M10: =RANK(L10,$L$4:$L$37) | N10: 0 | O10: 490815 | P10: =AVERAGEIFS(PO_Facts!$M$2:$M$4801,PO_Facts!$C$2:$C$4801,A10)
A11: VS08 | B11: Ratnamani Metals | C11: =COUNTIFS(PO_Facts!$C$2:$C$4801,A11) | D11: =SUMIFS(PO_Facts!$K$2:$K$4801,PO_Facts!$C$2:$C$4801,A11) | E11: =SUMIFS(PO_Facts!$Q$2:$Q$4801,PO_Facts!$C$2:$C$4801,A11) | F11: =D11-E11 | G11: =SUMIFS(PO_Facts!$S$2:$S$4801,PO_Facts!$C$2:$C$4801,A11) | H11: =MAX(0,SUMIFS(PO_Facts!$T$2:$T$4801,PO_Facts!$C$2:$C$4801,A11)) | I11: =SUMIFS(PO_Facts!$U$2:$U$4801,PO_Facts!$C$2:$C$4801,A11) | J11: =SUMIFS(Returns_Confirmed!$K$2:$K$241,Returns_Confirmed!$G$2:$G$241,A11) | K11: =SUMIFS(Returns_Inferred!$H$2:$H$4761,Returns_Inferred!$B$2:$B$4761,A11) | L11: =H11+I11+J11+K11 | M11: =RANK(L11,$L$4:$L$37) | N11: 66477 | O11: 1188820 | P11: =AVERAGEIFS(PO_Facts!$M$2:$M$4801,PO_Facts!$C$2:$C$4801,A11)
A12: VS09 | B12: MSP Steel | C12: =COUNTIFS(PO_Facts!$C$2:$C$4801,A12) | D12: =SUMIFS(PO_Facts!$K$2:$K$4801,PO_Facts!$C$2:$C$4801,A12) | E12: =SUMIFS(PO_Facts!$Q$2:$Q$4801,PO_Facts!$C$2:$C$4801,A12) | F12: =D12-E12 | G12: =SUMIFS(PO_Facts!$S$2:$S$4801,PO_Facts!$C$2:$C$4801,A12) | H12: =MAX(0,SUMIFS(PO_Facts!$T$2:$T$4801,PO_Facts!$C$2:$C$4801,A12)) | I12: =SUMIFS(PO_Facts!$U$2:$U$4801,PO_Facts!$C$2:$C$4801,A12) | J12: =SUMIFS(Returns_Confirmed!$K$2:$K$241,Returns_Confirmed!$G$2:$G$241,A12) | K12: =SUMIFS(Returns_Inferred!$H$2:$H$4761,Returns_Inferred!$B$2:$B$4761,A12) | L12: =H12+I12+J12+K12 | M12: =RANK(L12,$L$4:$L$37) | N12: 0 | O12: 989282 | P12: =AVERAGEIFS(PO_Facts!$M$2:$M$4801,PO_Facts!$C$2:$C$4801,A12)
A13: VS10 | B13: Gallantt Metal | C13: =COUNTIFS(PO_Facts!$C$2:$C$4801,A13) | D13: =SUMIFS(PO_Facts!$K$2:$K$4801,PO_Facts!$C$2:$C$4801,A13) | E13: =SUMIFS(PO_Facts!$Q$2:$Q$4801,PO_Facts!$C$2:$C$4801,A13) | F13: =D13-E13 | G13: =SUMIFS(PO_Facts!$S$2:$S$4801,PO_Facts!$C$2:$C$4801,A13) | H13: =MAX(0,SUMIFS(PO_Facts!$T$2:$T$4801,PO_Facts!$C$2:$C$4801,A13)) | I13: =SUMIFS(PO_Facts!$U$2:$U$4801,PO_Facts!$C$2:$C$4801,A13) | J13: =SUMIFS(Returns_Confirmed!$K$2:$K$241,Returns_Confirmed!$G$2:$G$241,A13) | K13: =SUMIFS(Returns_Inferred!$H$2:$H$4761,Returns_Inferred!$B$2:$B$4761,A13) | L13: =H13+I13+J13+K13 | M13: =RANK(L13,$L$4:$L$37) | N13: 137225 | O13: 1390500 | P13: =AVERAGEIFS(PO_Facts!$M$2:$M$4801,PO_Facts!$C$2:$C$4801,A13)
A14: VS11 | B14: Sai Steel | C14: =COUNTIFS(PO_Facts!$C$2:$C$4801,A14) | D14: =SUMIFS(PO_Facts!$K$2:$K$4801,PO_Facts!$C$2:$C$4801,A14) | E14: =SUMIFS(PO_Facts!$Q$2:$Q$4801,PO_Facts!$C$2:$C$4801,A14) | F14: =D14-E14 | G14: =SUMIFS(PO_Facts!$S$2:$S$4801,PO_Facts!$C$2:$C$4801,A14) | H14: =MAX(0,SUMIFS(PO_Facts!$T$2:$T$4801,PO_Facts!$C$2:$C$4801,A14)) | I14: =SUMIFS(PO_Facts!$U$2:$U$4801,PO_Facts!$C$2:$C$4801,A14) | J14: =SUMIFS(Returns_Confirmed!$K$2:$K$241,Returns_Confirmed!$G$2:$G$241,A14) | K14: =SUMIFS(Returns_Inferred!$H$2:$H$4761,Returns_Inferred!$B$2:$B$4761,A14) | L14: =H14+I14+J14+K14 | M14: =RANK(L14,$L$4:$L$37) | N14: 222735 | O14: 1389189 | P14: =AVERAGEIFS(PO_Facts!$M$2:$M$4801,PO_Facts!$C$2:$C$4801,A14)
A15: VS12 | B15: Nutan Tubes | C15: =COUNTIFS(PO_Facts!$C$2:$C$4801,A15) | D15: =SUMIFS(PO_Facts!$K$2:$K$4801,PO_Facts!$C$2:$C$4801,A15) | E15: =SUMIFS(PO_Facts!$Q$2:$Q$4801,PO_Facts!$C$2:$C$4801,A15) | F15: =D15-E15 | G15: =SUMIFS(PO_Facts!$S$2:$S$4801,PO_Facts!$C$2:$C$4801,A15) | H15: =MAX(0,SUMIFS(PO_Facts!$T$2:$T$4801,PO_Facts!$C$2:$C$4801,A15)) | I15: =SUMIFS(PO_Facts!$U$2:$U$4801,PO_Facts!$C$2:$C$4801,A15) | J15: =SUMIFS(Returns_Confirmed!$K$2:$K$241,Returns_Confirmed!$G$2:$G$241,A15) | K15: =SUMIFS(Returns_Inferred!$H$2:$H$4761,Returns_Inferred!$B$2:$B$4761,A15) | L15: =H15+I15+J15+K15 | M15: =RANK(L15,$L$4:$L$37) | N15: 4684100 | O15: 7799582 | P15: =AVERAGEIFS(PO_Facts!$M$2:$M$4801,PO_Facts!$C$2:$C$4801,A15)
... A37: VS34 | B37: Supreme Fittings | C37: =COUNTIFS(PO_Facts!$C$2:$C$4801,A37) | D37: =SUMIFS(PO_Facts!$K$2:$K$4801,PO_Facts!$C$2:$C$4801,A37) | E37: =SUMIFS(PO_Facts!$Q$2:$Q$4801,PO_Facts!$C$2:$C$4801,A37) | F37: =D37-E37 | G37: =SUMIFS(PO_Facts!$S$2:$S$4801,PO_Facts!$C$2:$C$4801,A37) | H37: =MAX(0,SUMIFS(PO_Facts!$T$2:$T$4801,PO_Facts!$C$2:$C$4801,A37)) | I37: =SUMIFS(PO_Facts!$U$2:$U$4801,PO_Facts!$C$2:$C$4801,A37) | J37: =SUMIFS(Returns_Confirmed!$K$2:$K$241,Returns_Confirmed!$G$2:$G$241,A37) | K37: =SUMIFS(Returns_Inferred!$H$2:$H$4761,Returns_Inferred!$B$2:$B$4761,A37) | L37: =H37+I37+J37+K37 | M37: =RANK(L37,$L$4:$L$37) | N37: 28873 | O37: 1163396 | P37: =AVERAGEIFS(PO_Facts!$M$2:$M$4801,PO_Facts!$C$2:$C$4801,A37)
B38: PANEL TOTAL | C38: =SUM(C4:C37) | D38: =SUM(D4:D37) | E38: =SUM(E4:E37) | F38: =SUM(F4:F37) | G38: =SUM(G4:G37) | H38: =SUM(H4:H37) | I38: =SUM(I4:I37) | J38: =SUM(J4:J37) | ... L38: =SUM(L4:L37)
A40: A = invoice_amount_billed - quantity_received x unit_price_quoted. A* = A minus the panel-normal part (floored at 0 per supplier). B = rejection_qty x unit price (rejected goods are inside received qty and were billed).
A41: C = confirmed returns, capped per batch. D = probability-weighted expected value of the 140 unattributed returns (80% range in columns N-O, from 4,000 simulated assignments).
A42: Price premium and late-delivery carrying cost are NOT in the headline: no supplier shows a statistically significant price premium, and the late cost is an assumption.

Sheet Scorecard
A1: 34-supplier scorecard - performance only (no relationship years). Score 100 = panel median or better, 0 = as bad as the worst supplier on that metric
A3: supplier_id | B3: supplier_name | C3: PO count | D3: Short delivery % of ordered qty | E3: Late POs % | F3: Avg days late | G3: Rejection % of received | H3: Returns per 1,000 MT received | I3: Price vs panel z-score | J3: Score: short | K3: Score: late | L3: Score: rejection | M3: Score: returns | N3: Score: price | O3: COMPOSITE | P3: Tier | Q3: Rank (1 = worst) | R3: MT received
A4: VS01 | B4: Jindal Steel & Power | C4: =COUNTIFS(PO_Facts!$C$2:$C$4801,A4) | D4: =SUMIFS(PO_Facts!$N$2:$N$4801,PO_Facts!$C$2:$C$4801,A4)/SUMIFS(PO_Facts!$F$2:$F$4801,PO_Facts!$C$2:$C$4801,A4)*100 | E4: =COUNTIFS(PO_Facts!$C$2:$C$4801,A4,PO_Facts!$O$2:$O$4801,">0")/C4*100 | F4: =AVERAGEIFS(PO_Facts!$O$2:$O$4801,PO_Facts!$C$2:$C$4801,A4) | G4: =SUMIFS(PO_Facts!$L$2:$L$4801,PO_Facts!$C$2:$C$4801,A4)/R4*100 | H4: =(COUNTIFS(Returns_Confirmed!$G$2:$G$241,A4)+SUMIFS(Returns_Inferred!$C$2:$C$4761,Returns_Inferred!$B$2:$B$4761,A4))/R4*1000 | I4: -1.5 | J4: =100*(1-MIN(1,MAX(0,(D4-MEDIAN($D$4:$D$37))/(MAX($D$4:$D$37)-MEDIAN($D$4:$D$37))))) | K4: =100*(1-MIN(1,MAX(0,(F4-MEDIAN($F$4:$F$37))/(MAX($F$4:$F$37)-MEDIAN($F$4:$F$37))))) | L4: =100*(1-MIN(1,MAX(0,(G4-MEDIAN($G$4:$G$37))/(MAX($G$4:$G$37)-MEDIAN($G$4:$G$37))))) | M4: =100*(1-MIN(1,MAX(0,(H4-MEDIAN($H$4:$H$37))/(MAX($H$4:$H$37)-MEDIAN($H$4:$H$37))))) | N4: =100*(1-MIN(1,MAX(I4,0)/Assumptions!$B$13)) | O4: =J4*Assumptions!$B$7+K4*Assumptions!$B$8+L4*Assumptions!$B$9+M4*Assumptions!$B$10+N4*Assumptions!$B$11 | P4: =IF(O4<Assumptions!$B$14,"POOR",IF(O4<Assumptions!$C$14,"WATCH","ACCEPTABLE")) | Q4: =RANK(O4,$O$4:$O$37,1) | R4: =SUMIFS(PO_Facts!$J$2:$J$4801,PO_Facts!$C$2:$C$4801,A4)
A5: VS02 | B5: SAIL Distribution | C5: =COUNTIFS(PO_Facts!$C$2:$C$4801,A5) | D5: =SUMIFS(PO_Facts!$N$2:$N$4801,PO_Facts!$C$2:$C$4801,A5)/SUMIFS(PO_Facts!$F$2:$F$4801,PO_Facts!$C$2:$C$4801,A5)*100 | E5: =COUNTIFS(PO_Facts!$C$2:$C$4801,A5,PO_Facts!$O$2:$O$4801,">0")/C5*100 | F5: =AVERAGEIFS(PO_Facts!$O$2:$O$4801,PO_Facts!$C$2:$C$4801,A5) | G5: =SUMIFS(PO_Facts!$L$2:$L$4801,PO_Facts!$C$2:$C$4801,A5)/R5*100 | H5: =(COUNTIFS(Returns_Confirmed!$G$2:$G$241,A5)+SUMIFS(Returns_Inferred!$C$2:$C$4761,Returns_Inferred!$B$2:$B$4761,A5))/R5*1000 | I5: -0.35 | J5: =100*(1-MIN(1,MAX(0,(D5-MEDIAN($D$4:$D$37))/(MAX($D$4:$D$37)-MEDIAN($D$4:$D$37))))) | K5: =100*(1-MIN(1,MAX(0,(F5-MEDIAN($F$4:$F$37))/(MAX($F$4:$F$37)-MEDIAN($F$4:$F$37))))) | L5: =100*(1-MIN(1,MAX(0,(G5-MEDIAN($G$4:$G$37))/(MAX($G$4:$G$37)-MEDIAN($G$4:$G$37))))) | M5: =100*(1-MIN(1,MAX(0,(H5-MEDIAN($H$4:$H$37))/(MAX($H$4:$H$37)-MEDIAN($H$4:$H$37))))) | N5: =100*(1-MIN(1,MAX(I5,0)/Assumptions!$B$13)) | O5: =J5*Assumptions!$B$7+K5*Assumptions!$B$8+L5*Assumptions!$B$9+M5*Assumptions!$B$10+N5*Assumptions!$B$11 | P5: =IF(O5<Assumptions!$B$14,"POOR",IF(O5<Assumptions!$C$14,"WATCH","ACCEPTABLE")) | Q5: =RANK(O5,$O$4:$O$37,1) | R5: =SUMIFS(PO_Facts!$J$2:$J$4801,PO_Facts!$C$2:$C$4801,A5)
A6: VS03 | B6: Tata Steel Service | C6: =COUNTIFS(PO_Facts!$C$2:$C$4801,A6) | D6: =SUMIFS(PO_Facts!$N$2:$N$4801,PO_Facts!$C$2:$C$4801,A6)/SUMIFS(PO_Facts!$F$2:$F$4801,PO_Facts!$C$2:$C$4801,A6)*100 | E6: =COUNTIFS(PO_Facts!$C$2:$C$4801,A6,PO_Facts!$O$2:$O$4801,">0")/C6*100 | F6: =AVERAGEIFS(PO_Facts!$O$2:$O$4801,PO_Facts!$C$2:$C$4801,A6) | G6: =SUMIFS(PO_Facts!$L$2:$L$4801,PO_Facts!$C$2:$C$4801,A6)/R6*100 | H6: =(COUNTIFS(Returns_Confirmed!$G$2:$G$241,A6)+SUMIFS(Returns_Inferred!$C$2:$C$4761,Returns_Inferred!$B$2:$B$4761,A6))/R6*1000 | I6: 1.54 | J6: =100*(1-MIN(1,MAX(0,(D6-MEDIAN($D$4:$D$37))/(MAX($D$4:$D$37)-MEDIAN($D$4:$D$37))))) | K6: =100*(1-MIN(1,MAX(0,(F6-MEDIAN($F$4:$F$37))/(MAX($F$4:$F$37)-MEDIAN($F$4:$F$37))))) | L6: =100*(1-MIN(1,MAX(0,(G6-MEDIAN($G$4:$G$37))/(MAX($G$4:$G$37)-MEDIAN($G$4:$G$37))))) | M6: =100*(1-MIN(1,MAX(0,(H6-MEDIAN($H$4:$H$37))/(MAX($H$4:$H$37)-MEDIAN($H$4:$H$37))))) | N6: =100*(1-MIN(1,MAX(I6,0)/Assumptions!$B$13)) | O6: =J6*Assumptions!$B$7+K6*Assumptions!$B$8+L6*Assumptions!$B$9+M6*Assumptions!$B$10+N6*Assumptions!$B$11 | P6: =IF(O6<Assumptions!$B$14,"POOR",IF(O6<Assumptions!$C$14,"WATCH","ACCEPTABLE")) | Q6: =RANK(O6,$O$4:$O$37,1) | R6: =SUMIFS(PO_Facts!$J$2:$J$4801,PO_Facts!$C$2:$C$4801,A6)
A7: VS04 | B7: Shyam Metalics | C7: =COUNTIFS(PO_Facts!$C$2:$C$4801,A7) | D7: =SUMIFS(PO_Facts!$N$2:$N$4801,PO_Facts!$C$2:$C$4801,A7)/SUMIFS(PO_Facts!$F$2:$F$4801,PO_Facts!$C$2:$C$4801,A7)*100 | E7: =COUNTIFS(PO_Facts!$C$2:$C$4801,A7,PO_Facts!$O$2:$O$4801,">0")/C7*100 | F7: =AVERAGEIFS(PO_Facts!$O$2:$O$4801,PO_Facts!$C$2:$C$4801,A7) | G7: =SUMIFS(PO_Facts!$L$2:$L$4801,PO_Facts!$C$2:$C$4801,A7)/R7*100 | H7: =(COUNTIFS(Returns_Confirmed!$G$2:$G$241,A7)+SUMIFS(Returns_Inferred!$C$2:$C$4761,Returns_Inferred!$B$2:$B$4761,A7))/R7*1000 | I7: -1.62 | J7: =100*(1-MIN(1,MAX(0,(D7-MEDIAN($D$4:$D$37))/(MAX($D$4:$D$37)-MEDIAN($D$4:$D$37))))) | K7: =100*(1-MIN(1,MAX(0,(F7-MEDIAN($F$4:$F$37))/(MAX($F$4:$F$37)-MEDIAN($F$4:$F$37))))) | L7: =100*(1-MIN(1,MAX(0,(G7-MEDIAN($G$4:$G$37))/(MAX($G$4:$G$37)-MEDIAN($G$4:$G$37))))) | M7: =100*(1-MIN(1,MAX(0,(H7-MEDIAN($H$4:$H$37))/(MAX($H$4:$H$37)-MEDIAN($H$4:$H$37))))) | N7: =100*(1-MIN(1,MAX(I7,0)/Assumptions!$B$13)) | O7: =J7*Assumptions!$B$7+K7*Assumptions!$B$8+L7*Assumptions!$B$9+M7*Assumptions!$B$10+N7*Assumptions!$B$11 | P7: =IF(O7<Assumptions!$B$14,"POOR",IF(O7<Assumptions!$C$14,"WATCH","ACCEPTABLE")) | Q7: =RANK(O7,$O$4:$O$37,1) | R7: =SUMIFS(PO_Facts!$J$2:$J$4801,PO_Facts!$C$2:$C$4801,A7)
A8: VS05 | B8: Bhushan Steel | C8: =COUNTIFS(PO_Facts!$C$2:$C$4801,A8) | D8: =SUMIFS(PO_Facts!$N$2:$N$4801,PO_Facts!$C$2:$C$4801,A8)/SUMIFS(PO_Facts!$F$2:$F$4801,PO_Facts!$C$2:$C$4801,A8)*100 | E8: =COUNTIFS(PO_Facts!$C$2:$C$4801,A8,PO_Facts!$O$2:$O$4801,">0")/C8*100 | F8: =AVERAGEIFS(PO_Facts!$O$2:$O$4801,PO_Facts!$C$2:$C$4801,A8) | G8: =SUMIFS(PO_Facts!$L$2:$L$4801,PO_Facts!$C$2:$C$4801,A8)/R8*100 | H8: =(COUNTIFS(Returns_Confirmed!$G$2:$G$241,A8)+SUMIFS(Returns_Inferred!$C$2:$C$4761,Returns_Inferred!$B$2:$B$4761,A8))/R8*1000 | I8: -1.44 | J8: =100*(1-MIN(1,MAX(0,(D8-MEDIAN($D$4:$D$37))/(MAX($D$4:$D$37)-MEDIAN($D$4:$D$37))))) | K8: =100*(1-MIN(1,MAX(0,(F8-MEDIAN($F$4:$F$37))/(MAX($F$4:$F$37)-MEDIAN($F$4:$F$37))))) | L8: =100*(1-MIN(1,MAX(0,(G8-MEDIAN($G$4:$G$37))/(MAX($G$4:$G$37)-MEDIAN($G$4:$G$37))))) | M8: =100*(1-MIN(1,MAX(0,(H8-MEDIAN($H$4:$H$37))/(MAX($H$4:$H$37)-MEDIAN($H$4:$H$37))))) | N8: =100*(1-MIN(1,MAX(I8,0)/Assumptions!$B$13)) | O8: =J8*Assumptions!$B$7+K8*Assumptions!$B$8+L8*Assumptions!$B$9+M8*Assumptions!$B$10+N8*Assumptions!$B$11 | P8: =IF(O8<Assumptions!$B$14,"POOR",IF(O8<Assumptions!$C$14,"WATCH","ACCEPTABLE")) | Q8: =RANK(O8,$O$4:$O$37,1) | R8: =SUMIFS(PO_Facts!$J$2:$J$4801,PO_Facts!$C$2:$C$4801,A8)
A9: VS06 | B9: APL Apollo Tubes | C9: =COUNTIFS(PO_Facts!$C$2:$C$4801,A9) | D9: =SUMIFS(PO_Facts!$N$2:$N$4801,PO_Facts!$C$2:$C$4801,A9)/SUMIFS(PO_Facts!$F$2:$F$4801,PO_Facts!$C$2:$C$4801,A9)*100 | E9: =COUNTIFS(PO_Facts!$C$2:$C$4801,A9,PO_Facts!$O$2:$O$4801,">0")/C9*100 | F9: =AVERAGEIFS(PO_Facts!$O$2:$O$4801,PO_Facts!$C$2:$C$4801,A9) | G9: =SUMIFS(PO_Facts!$L$2:$L$4801,PO_Facts!$C$2:$C$4801,A9)/R9*100 | H9: =(COUNTIFS(Returns_Confirmed!$G$2:$G$241,A9)+SUMIFS(Returns_Inferred!$C$2:$C$4761,Returns_Inferred!$B$2:$B$4761,A9))/R9*1000 | I9: 0.92 | J9: =100*(1-MIN(1,MAX(0,(D9-MEDIAN($D$4:$D$37))/(MAX($D$4:$D$37)-MEDIAN($D$4:$D$37))))) | K9: =100*(1-MIN(1,MAX(0,(F9-MEDIAN($F$4:$F$37))/(MAX($F$4:$F$37)-MEDIAN($F$4:$F$37))))) | L9: =100*(1-MIN(1,MAX(0,(G9-MEDIAN($G$4:$G$37))/(MAX($G$4:$G$37)-MEDIAN($G$4:$G$37))))) | M9: =100*(1-MIN(1,MAX(0,(H9-MEDIAN($H$4:$H$37))/(MAX($H$4:$H$37)-MEDIAN($H$4:$H$37))))) | N9: =100*(1-MIN(1,MAX(I9,0)/Assumptions!$B$13)) | O9: =J9*Assumptions!$B$7+K9*Assumptions!$B$8+L9*Assumptions!$B$9+M9*Assumptions!$B$10+N9*Assumptions!$B$11 | P9: =IF(O9<Assumptions!$B$14,"POOR",IF(O9<Assumptions!$C$14,"WATCH","ACCEPTABLE")) | Q9: =RANK(O9,$O$4:$O$37,1) | R9: =SUMIFS(PO_Facts!$J$2:$J$4801,PO_Facts!$C$2:$C$4801,A9)
A10: VS07 | B10: Prakash Industries | C10: =COUNTIFS(PO_Facts!$C$2:$C$4801,A10) | D10: =SUMIFS(PO_Facts!$N$2:$N$4801,PO_Facts!$C$2:$C$4801,A10)/SUMIFS(PO_Facts!$F$2:$F$4801,PO_Facts!$C$2:$C$4801,A10)*100 | E10: =COUNTIFS(PO_Facts!$C$2:$C$4801,A10,PO_Facts!$O$2:$O$4801,">0")/C10*100 | F10: =AVERAGEIFS(PO_Facts!$O$2:$O$4801,PO_Facts!$C$2:$C$4801,A10) | G10: =SUMIFS(PO_Facts!$L$2:$L$4801,PO_Facts!$C$2:$C$4801,A10)/R10*100 | H10: =(COUNTIFS(Returns_Confirmed!$G$2:$G$241,A10)+SUMIFS(Returns_Inferred!$C$2:$C$4761,Returns_Inferred!$B$2:$B$4761,A10))/R10*1000 | I10: -1.31 | J10: =100*(1-MIN(1,MAX(0,(D10-MEDIAN($D$4:$D$37))/(MAX($D$4:$D$37)-MEDIAN($D$4:$D$37))))) | K10: =100*(1-MIN(1,MAX(0,(F10-MEDIAN($F$4:$F$37))/(MAX($F$4:$F$37)-MEDIAN($F$4:$F$37))))) | L10: =100*(1-MIN(1,MAX(0,(G10-MEDIAN($G$4:$G$37))/(MAX($G$4:$G$37)-MEDIAN($G$4:$G$37))))) | M10: =100*(1-MIN(1,MAX(0,(H10-MEDIAN($H$4:$H$37))/(MAX($H$4:$H$37)-MEDIAN($H$4:$H$37))))) | N10: =100*(1-MIN(1,MAX(I10,0)/Assumptions!$B$13)) | O10: =J10*Assumptions!$B$7+K10*Assumptions!$B$8+L10*Assumptions!$B$9+M10*Assumptions!$B$10+N10*Assumptions!$B$11 | P10: =IF(O10<Assumptions!$B$14,"POOR",IF(O10<Assumptions!$C$14,"WATCH","ACCEPTABLE")) | Q10: =RANK(O10,$O$4:$O$37,1) | R10: =SUMIFS(PO_Facts!$J$2:$J$4801,PO_Facts!$C$2:$C$4801,A10)
A11: VS08 | B11: Ratnamani Metals | C11: =COUNTIFS(PO_Facts!$C$2:$C$4801,A11) | D11: =SUMIFS(PO_Facts!$N$2:$N$4801,PO_Facts!$C$2:$C$4801,A11)/SUMIFS(PO_Facts!$F$2:$F$4801,PO_Facts!$C$2:$C$4801,A11)*100 | E11: =COUNTIFS(PO_Facts!$C$2:$C$4801,A11,PO_Facts!$O$2:$O$4801,">0")/C11*100 | F11: =AVERAGEIFS(PO_Facts!$O$2:$O$4801,PO_Facts!$C$2:$C$4801,A11) | G11: =SUMIFS(PO_Facts!$L$2:$L$4801,PO_Facts!$C$2:$C$4801,A11)/R11*100 | H11: =(COUNTIFS(Returns_Confirmed!$G$2:$G$241,A11)+SUMIFS(Returns_Inferred!$C$2:$C$4761,Returns_Inferred!$B$2:$B$4761,A11))/R11*1000 | I11: -0.45 | J11: =100*(1-MIN(1,MAX(0,(D11-MEDIAN($D$4:$D$37))/(MAX($D$4:$D$37)-MEDIAN($D$4:$D$37))))) | K11: =100*(1-MIN(1,MAX(0,(F11-MEDIAN($F$4:$F$37))/(MAX($F$4:$F$37)-MEDIAN($F$4:$F$37))))) | L11: =100*(1-MIN(1,MAX(0,(G11-MEDIAN($G$4:$G$37))/(MAX($G$4:$G$37)-MEDIAN($G$4:$G$37))))) | M11: =100*(1-MIN(1,MAX(0,(H11-MEDIAN($H$4:$H$37))/(MAX($H$4:$H$37)-MEDIAN($H$4:$H$37))))) | N11: =100*(1-MIN(1,MAX(I11,0)/Assumptions!$B$13)) | O11: =J11*Assumptions!$B$7+K11*Assumptions!$B$8+L11*Assumptions!$B$9+M11*Assumptions!$B$10+N11*Assumptions!$B$11 | P11: =IF(O11<Assumptions!$B$14,"POOR",IF(O11<Assumptions!$C$14,"WATCH","ACCEPTABLE")) | Q11: =RANK(O11,$O$4:$O$37,1) | R11: =SUMIFS(PO_Facts!$J$2:$J$4801,PO_Facts!$C$2:$C$4801,A11)
A12: VS09 | B12: MSP Steel | C12: =COUNTIFS(PO_Facts!$C$2:$C$4801,A12) | D12: =SUMIFS(PO_Facts!$N$2:$N$4801,PO_Facts!$C$2:$C$4801,A12)/SUMIFS(PO_Facts!$F$2:$F$4801,PO_Facts!$C$2:$C$4801,A12)*100 | E12: =COUNTIFS(PO_Facts!$C$2:$C$4801,A12,PO_Facts!$O$2:$O$4801,">0")/C12*100 | F12: =AVERAGEIFS(PO_Facts!$O$2:$O$4801,PO_Facts!$C$2:$C$4801,A12) | G12: =SUMIFS(PO_Facts!$L$2:$L$4801,PO_Facts!$C$2:$C$4801,A12)/R12*100 | H12: =(COUNTIFS(Returns_Confirmed!$G$2:$G$241,A12)+SUMIFS(Returns_Inferred!$C$2:$C$4761,Returns_Inferred!$B$2:$B$4761,A12))/R12*1000 | I12: 1.22 | J12: =100*(1-MIN(1,MAX(0,(D12-MEDIAN($D$4:$D$37))/(MAX($D$4:$D$37)-MEDIAN($D$4:$D$37))))) | K12: =100*(1-MIN(1,MAX(0,(F12-MEDIAN($F$4:$F$37))/(MAX($F$4:$F$37)-MEDIAN($F$4:$F$37))))) | L12: =100*(1-MIN(1,MAX(0,(G12-MEDIAN($G$4:$G$37))/(MAX($G$4:$G$37)-MEDIAN($G$4:$G$37))))) | M12: =100*(1-MIN(1,MAX(0,(H12-MEDIAN($H$4:$H$37))/(MAX($H$4:$H$37)-MEDIAN($H$4:$H$37))))) | N12: =100*(1-MIN(1,MAX(I12,0)/Assumptions!$B$13)) | O12: =J12*Assumptions!$B$7+K12*Assumptions!$B$8+L12*Assumptions!$B$9+M12*Assumptions!$B$10+N12*Assumptions!$B$11 | P12: =IF(O12<Assumptions!$B$14,"POOR",IF(O12<Assumptions!$C$14,"WATCH","ACCEPTABLE")) | Q12: =RANK(O12,$O$4:$O$37,1) | R12: =SUMIFS(PO_Facts!$J$2:$J$4801,PO_Facts!$C$2:$C$4801,A12)
A13: VS10 | B13: Gallantt Metal | C13: =COUNTIFS(PO_Facts!$C$2:$C$4801,A13) | D13: =SUMIFS(PO_Facts!$N$2:$N$4801,PO_Facts!$C$2:$C$4801,A13)/SUMIFS(PO_Facts!$F$2:$F$4801,PO_Facts!$C$2:$C$4801,A13)*100 | E13: =COUNTIFS(PO_Facts!$C$2:$C$4801,A13,PO_Facts!$O$2:$O$4801,">0")/C13*100 | F13: =AVERAGEIFS(PO_Facts!$O$2:$O$4801,PO_Facts!$C$2:$C$4801,A13) | G13: =SUMIFS(PO_Facts!$L$2:$L$4801,PO_Facts!$C$2:$C$4801,A13)/R13*100 | H13: =(COUNTIFS(Returns_Confirmed!$G$2:$G$241,A13)+SUMIFS(Returns_Inferred!$C$2:$C$4761,Returns_Inferred!$B$2:$B$4761,A13))/R13*1000 | I13: 0.43 | J13: =100*(1-MIN(1,MAX(0,(D13-MEDIAN($D$4:$D$37))/(MAX($D$4:$D$37)-MEDIAN($D$4:$D$37))))) | K13: =100*(1-MIN(1,MAX(0,(F13-MEDIAN($F$4:$F$37))/(MAX($F$4:$F$37)-MEDIAN($F$4:$F$37))))) | L13: =100*(1-MIN(1,MAX(0,(G13-MEDIAN($G$4:$G$37))/(MAX($G$4:$G$37)-MEDIAN($G$4:$G$37))))) | M13: =100*(1-MIN(1,MAX(0,(H13-MEDIAN($H$4:$H$37))/(MAX($H$4:$H$37)-MEDIAN($H$4:$H$37))))) | N13: =100*(1-MIN(1,MAX(I13,0)/Assumptions!$B$13)) | O13: =J13*Assumptions!$B$7+K13*Assumptions!$B$8+L13*Assumptions!$B$9+M13*Assumptions!$B$10+N13*Assumptions!$B$11 | P13: =IF(O13<Assumptions!$B$14,"POOR",IF(O13<Assumptions!$C$14,"WATCH","ACCEPTABLE")) | Q13: =RANK(O13,$O$4:$O$37,1) | R13: =SUMIFS(PO_Facts!$J$2:$J$4801,PO_Facts!$C$2:$C$4801,A13)
A14: VS11 | B14: Sai Steel | C14: =COUNTIFS(PO_Facts!$C$2:$C$4801,A14) | D14: =SUMIFS(PO_Facts!$N$2:$N$4801,PO_Facts!$C$2:$C$4801,A14)/SUMIFS(PO_Facts!$F$2:$F$4801,PO_Facts!$C$2:$C$4801,A14)*100 | E14: =COUNTIFS(PO_Facts!$C$2:$C$4801,A14,PO_Facts!$O$2:$O$4801,">0")/C14*100 | F14: =AVERAGEIFS(PO_Facts!$O$2:$O$4801,PO_Facts!$C$2:$C$4801,A14) | G14: =SUMIFS(PO_Facts!$L$2:$L$4801,PO_Facts!$C$2:$C$4801,A14)/R14*100 | H14: =(COUNTIFS(Returns_Confirmed!$G$2:$G$241,A14)+SUMIFS(Returns_Inferred!$C$2:$C$4761,Returns_Inferred!$B$2:$B$4761,A14))/R14*1000 | I14: 0.48 | J14: =100*(1-MIN(1,MAX(0,(D14-MEDIAN($D$4:$D$37))/(MAX($D$4:$D$37)-MEDIAN($D$4:$D$37))))) | K14: =100*(1-MIN(1,MAX(0,(F14-MEDIAN($F$4:$F$37))/(MAX($F$4:$F$37)-MEDIAN($F$4:$F$37))))) | L14: =100*(1-MIN(1,MAX(0,(G14-MEDIAN($G$4:$G$37))/(MAX($G$4:$G$37)-MEDIAN($G$4:$G$37))))) | M14: =100*(1-MIN(1,MAX(0,(H14-MEDIAN($H$4:$H$37))/(MAX($H$4:$H$37)-MEDIAN($H$4:$H$37))))) | N14: =100*(1-MIN(1,MAX(I14,0)/Assumptions!$B$13)) | O14: =J14*Assumptions!$B$7+K14*Assumptions!$B$8+L14*Assumptions!$B$9+M14*Assumptions!$B$10+N14*Assumptions!$B$11 | P14: =IF(O14<Assumptions!$B$14,"POOR",IF(O14<Assumptions!$C$14,"WATCH","ACCEPTABLE")) | Q14: =RANK(O14,$O$4:$O$37,1) | R14: =SUMIFS(PO_Facts!$J$2:$J$4801,PO_Facts!$C$2:$C$4801,A14)
A15: VS12 | B15: Nutan Tubes | C15: =COUNTIFS(PO_Facts!$C$2:$C$4801,A15) | D15: =SUMIFS(PO_Facts!$N$2:$N$4801,PO_Facts!$C$2:$C$4801,A15)/SUMIFS(PO_Facts!$F$2:$F$4801,PO_Facts!$C$2:$C$4801,A15)*100 | E15: =COUNTIFS(PO_Facts!$C$2:$C$4801,A15,PO_Facts!$O$2:$O$4801,">0")/C15*100 | F15: =AVERAGEIFS(PO_Facts!$O$2:$O$4801,PO_Facts!$C$2:$C$4801,A15) | G15: =SUMIFS(PO_Facts!$L$2:$L$4801,PO_Facts!$C$2:$C$4801,A15)/R15*100 | H15: =(COUNTIFS(Returns_Confirmed!$G$2:$G$241,A15)+SUMIFS(Returns_Inferred!$C$2:$C$4761,Returns_Inferred!$B$2:$B$4761,A15))/R15*1000 | I15: 0.43 | J15: =100*(1-MIN(1,MAX(0,(D15-MEDIAN($D$4:$D$37))/(MAX($D$4:$D$37)-MEDIAN($D$4:$D$37))))) | K15: =100*(1-MIN(1,MAX(0,(F15-MEDIAN($F$4:$F$37))/(MAX($F$4:$F$37)-MEDIAN($F$4:$F$37))))) | L15: =100*(1-MIN(1,MAX(0,(G15-MEDIAN($G$4:$G$37))/(MAX($G$4:$G$37)-MEDIAN($G$4:$G$37))))) | M15: =100*(1-MIN(1,MAX(0,(H15-MEDIAN($H$4:$H$37))/(MAX($H$4:$H$37)-MEDIAN($H$4:$H$37))))) | N15: =100*(1-MIN(1,MAX(I15,0)/Assumptions!$B$13)) | O15: =J15*Assumptions!$B$7+K15*Assumptions!$B$8+L15*Assumptions!$B$9+M15*Assumptions!$B$10+N15*Assumptions!$B$11 | P15: =IF(O15<Assumptions!$B$14,"POOR",IF(O15<Assumptions!$C$14,"WATCH","ACCEPTABLE")) | Q15: =RANK(O15,$O$4:$O$37,1) | R15: =SUMIFS(PO_Facts!$J$2:$J$4801,PO_Facts!$C$2:$C$4801,A15)
... A37: VS34 | B37: Supreme Fittings | C37: =COUNTIFS(PO_Facts!$C$2:$C$4801,A37) | D37: =SUMIFS(PO_Facts!$N$2:$N$4801,PO_Facts!$C$2:$C$4801,A37)/SUMIFS(PO_Facts!$F$2:$F$4801,PO_Facts!$C$2:$C$4801,A37)*100 | E37: =COUNTIFS(PO_Facts!$C$2:$C$4801,A37,PO_Facts!$O$2:$O$4801,">0")/C37*100 | F37: =AVERAGEIFS(PO_Facts!$O$2:$O$4801,PO_Facts!$C$2:$C$4801,A37) | G37: =SUMIFS(PO_Facts!$L$2:$L$4801,PO_Facts!$C$2:$C$4801,A37)/R37*100 | H37: =(COUNTIFS(Returns_Confirmed!$G$2:$G$241,A37)+SUMIFS(Returns_Inferred!$C$2:$C$4761,Returns_Inferred!$B$2:$B$4761,A37))/R37*1000 | I37: 0.97 | J37: =100*(1-MIN(1,MAX(0,(D37-MEDIAN($D$4:$D$37))/(MAX($D$4:$D$37)-MEDIAN($D$4:$D$37))))) | K37: =100*(1-MIN(1,MAX(0,(F37-MEDIAN($F$4:$F$37))/(MAX($F$4:$F$37)-MEDIAN($F$4:$F$37))))) | L37: =100*(1-MIN(1,MAX(0,(G37-MEDIAN($G$4:$G$37))/(MAX($G$4:$G$37)-MEDIAN($G$4:$G$37))))) | M37: =100*(1-MIN(1,MAX(0,(H37-MEDIAN($H$4:$H$37))/(MAX($H$4:$H$37)-MEDIAN($H$4:$H$37))))) | N37: =100*(1-MIN(1,MAX(I37,0)/Assumptions!$B$13)) | O37: =J37*Assumptions!$B$7+K37*Assumptions!$B$8+L37*Assumptions!$B$9+M37*Assumptions!$B$10+N37*Assumptions!$B$11 | P37: =IF(O37<Assumptions!$B$14,"POOR",IF(O37<Assumptions!$C$14,"WATCH","ACCEPTABLE")) | Q37: =RANK(O37,$O$4:$O$37,1) | R37: =SUMIFS(PO_Facts!$J$2:$J$4801,PO_Facts!$C$2:$C$4801,A37)
B38: Panel median | D38: =MEDIAN(D4:D37) | E38: =MEDIAN(E4:E37) | F38: =MEDIAN(F4:F37) | G38: =MEDIAN(G4:G37) | H38: =MEDIAN(H4:H37)
A40: Price z-score = mean % above/below the same material's panel average that year, divided by its standard error (from the pipeline). Price is scored by statistical evidence, so noise is not penalised.

Sheet PO_Facts
A1: po_id | B1: po_date | C1: supplier_id | D1: material_id | E1: in_master | F1: qty_ordered_MT | G1: unit_price_quoted | H1: delivery_promised | I1: receipt_date | J1: qty_received_MT | K1: invoice_billed | L1: rejection_qty_MT | M1: arora_days_late_paying | N1: short_qty_MT | O1: days_late_delivery | P1: ordered_value | Q1: received_value | R1: BILLING GAP (billed - received x price) | S1: baseline_gap | T1: excess_gap | U1: rejection_loss
A2: PO-2021-0000 | B2: 44351 | C2: VS29 | D2: Spring Steel | E2: N | F2: 5.8 | G2: 93910.87 | H2: 44362 | I2: 44363 | J2: 5.78 | K2: 544683.05 | L2: 0 | M2: 0 | N2: =F2-J2 | O2: =I2-H2 | P2: =F2*G2 | Q2: =J2*G2 | R2: =K2-Q2 | S2: =P2*Assumptions!$B$3/100 | T2: =R2-S2 | U2: =L2*G2
A3: PO-2021-0001 | B3: 44227 | C3: VS06 | D3: HR Coils | E3: N | F3: 9.15 | G3: 81423.08 | H3: 44233 | I3: 44233 | J3: 9.06 | K3: 745021.18 | L3: 0 | M3: 21 | N3: =F3-J3 | O3: =I3-H3 | P3: =F3*G3 | Q3: =J3*G3 | R3: =K3-Q3 | S3: =P3*Assumptions!$B$3/100 | T3: =R3-S3 | U3: =L3*G3
A4: PO-2021-0002 | B4: 45018 | C4: VS04 | D4: MS Sheets | E4: N | F4: 19.57 | G4: 118898.16 | H4: 45025 | I4: 45028 | J4: 19.42 | K4: 2326837 | L4: 0 | M4: 14 | N4: =F4-J4 | O4: =I4-H4 | P4: =F4*G4 | Q4: =J4*G4 | R4: =K4-Q4 | S4: =P4*Assumptions!$B$3/100 | T4: =R4-S4 | U4: =L4*G4
A5: PO-2021-0003 | B5: 45128 | C5: VS19 | D5: GI Wire | E5: N | F5: 35.13 | G5: 103779.41 | H5: 45143 | I5: 45148 | J5: 33.7 | K5: 3645770.7 | L5: 1.55 | M5: 21 | N5: =F5-J5 | O5: =I5-H5 | P5: =F5*G5 | Q5: =J5*G5 | R5: =K5-Q5 | S5: =P5*Assumptions!$B$3/100 | T5: =R5-S5 | U5: =L5*G5
A6: PO-2021-0004 | B6: 45193 | C6: VS10 | D6: GI Sheets | E6: N | F6: 15.54 | G6: 117653.2 | H6: 45205 | I6: 45206 | J6: 15.5 | K6: 1828330.7 | L6: 0 | M6: 16 | N6: =F6-J6 | O6: =I6-H6 | P6: =F6*G6 | Q6: =J6*G6 | R6: =K6-Q6 | S6: =P6*Assumptions!$B$3/100 | T6: =R6-S6 | U6: =L6*G6
A7: PO-2021-0005 | B7: 44321 | C7: VS21 | D7: GI Pipes | E7: N | F7: 3.46 | G7: 80759.14 | H7: 44332 | I7: 44334 | J7: 3.43 | K7: 279426.62 | L7: 0 | M7: 1 | N7: =F7-J7 | O7: =I7-H7 | P7: =F7*G7 | Q7: =J7*G7 | R7: =K7-Q7 | S7: =P7*Assumptions!$B$3/100 | T7: =R7-S7 | U7: =L7*G7
A8: PO-2021-0006 | B8: 44519 | C8: VS04 | D8: Hex Bars | E8: N | F8: 4.93 | G8: 58936.87 | H8: 44531 | I8: 44531 | J8: 4.9 | K8: 290558.77 | L8: 0 | M8: 19 | N8: =F8-J8 | O8: =I8-H8 | P8: =F8*G8 | Q8: =J8*G8 | R8: =K8-Q8 | S8: =P8*Assumptions!$B$3/100 | T8: =R8-S8 | U8: =L8*G8
A9: PO-2021-0007 | B9: 44336 | C9: VS16 | D9: MS Rods | E9: Y | F9: 6.87 | G9: 111771.55 | H9: 44342 | I9: 44343 | J9: 6.86 | K9: 767870.55 | L9: 0 | M9: 4 | N9: =F9-J9 | O9: =I9-H9 | P9: =F9*G9 | Q9: =J9*G9 | R9: =K9-Q9 | S9: =P9*Assumptions!$B$3/100 | T9: =R9-S9 | U9: =L9*G9
A10: PO-2021-0008 | B10: 44278 | C10: VS06 | D10: GI Wire | E10: N | F10: 33.21 | G10: 87392.02 | H10: 44286 | I10: 44287 | J10: 32.91 | K10: 2902289 | L10: 0 | M10: 17 | N10: =F10-J10 | O10: =I10-H10 | P10: =F10*G10 | Q10: =J10*G10 | R10: =K10-Q10 | S10: =P10*Assumptions!$B$3/100 | T10: =R10-S10 | U10: =L10*G10
A11: PO-2021-0009 | B11: 44731 | C11: VS14 | D11: MS Flats | E11: N | F11: 12.7 | G11: 74683.94 | H11: 44744 | I11: 44746 | J11: 12.64 | K11: 948486.04 | L11: 0 | M11: 1 | N11: =F11-J11 | O11: =I11-H11 | P11: =F11*G11 | Q11: =J11*G11 | R11: =K11-Q11 | S11: =P11*Assumptions!$B$3/100 | T11: =R11-S11 | U11: =L11*G11
A12: PO-2021-0010 | B12: 44811 | C12: VS30 | D12: MS Flats | E12: N | F12: 46.52 | G12: 115180.07 | H12: 44814 | I12: 44817 | J12: 46.32 | K12: 5358176.9 | L12: 0 | M12: 19 | N12: =F12-J12 | O12: =I12-H12 | P12: =F12*G12 | Q12: =J12*G12 | R12: =K12-Q12 | S12: =P12*Assumptions!$B$3/100 | T12: =R12-S12 | U12: =L12*G12
A13: PO-2021-0011 | B13: 45135 | C13: VS07 | D13: SS Pipes | E13: N | F13: 27.34 | G13: 82941.35 | H13: 45140 | I13: 45141 | J13: 27.16 | K13: 2267616.5 | L13: 0 | M13: 21 | N13: =F13-J13 | O13: =I13-H13 | P13: =F13*G13 | Q13: =J13*G13 | R13: =K13-Q13 | S13: =P13*Assumptions!$B$3/100 | T13: =R13-S13 | U13: =L13*G13
... A4801: PO-2023-4799 | B4801: 44671 | C4801: VS13 | D4801: Angles & Channels | E4801: N | F4801: 27.72 | G4801: 101700.4 | H4801: 44678 | I4801: 44681 | J4801: 27.48 | K4801: 2819135.1 | L4801: 0 | M4801: 12 | N4801: =F4801-J4801 | O4801: =I4801-H4801 | P4801: =F4801*G4801 | Q4801: =J4801*G4801 | R4801: =K4801-Q4801 | S4801: =P4801*Assumptions!$B$3/100 | T4801: =R4801-S4801 | U4801: =L4801*G4801

Sheet Returns_Confirmed
A1: return_id | B1: return_date | C1: client_id | D1: material_id | E1: qty_returned_MT | F1: reason | G1: supplier (as traced) | H1: matched_po (batch) | I1: qty_counted_MT (capped) | J1: batch_price | K1: VALUE (qty counted x price) | L1: batch received on/before return?
A2: RET-0002 | B2: 44633 | C2: Client-047 | D2: MS Sheets | E2: 4.12 | F2: Bend/warp | G2: VS12 | H2: PO-2023-3731 | I2: 4.12 | J2: 47472.58 | K2: =I2*J2 | L2: =IF(INDEX(PO_Facts!$I$2:$I$4801,MATCH(H2,PO_Facts!$A$2:$A$4801,0))<=B2,"yes","FALLBACK: no earlier batch")
A3: RET-0003 | B3: 44444 | C3: Client-068 | D3: GI Pipes | E3: 3.43 | F3: Bend/warp | G3: VS04 | H3: PO-2023-3204 | I3: 3.43 | J3: 92197.48 | K3: =I3*J3 | L3: =IF(INDEX(PO_Facts!$I$2:$I$4801,MATCH(H3,PO_Facts!$A$2:$A$4801,0))<=B3,"yes","FALLBACK: no earlier batch")
A4: RET-0005 | B4: 44527 | C4: Client-052 | D4: Angles & Channels | E4: 1.42 | F4: Wrong dimensions | G4: VS03 | H4: PO-2022-2449 | I4: 1.42 | J4: 68705.01 | K4: =I4*J4 | L4: =IF(INDEX(PO_Facts!$I$2:$I$4801,MATCH(H4,PO_Facts!$A$2:$A$4801,0))<=B4,"yes","FALLBACK: no earlier batch")
A5: RET-0007 | B5: 45109 | C5: Client-024 | D5: Angles & Channels | E5: 1.49 | F5: Bend/warp | G5: VS12 | H5: PO-2023-4772 | I5: 1.49 | J5: 71528 | K5: =I5*J5 | L5: =IF(INDEX(PO_Facts!$I$2:$I$4801,MATCH(H5,PO_Facts!$A$2:$A$4801,0))<=B5,"yes","FALLBACK: no earlier batch")
A6: RET-0008 | B6: 44766 | C6: Client-001 | D6: SS Pipes | E6: 0.87 | F6: Weight short | G6: VS12 | H6: PO-2022-1642 | I6: 0.87 | J6: 68164.61 | K6: =I6*J6 | L6: =IF(INDEX(PO_Facts!$I$2:$I$4801,MATCH(H6,PO_Facts!$A$2:$A$4801,0))<=B6,"yes","FALLBACK: no earlier batch")
A7: RET-0009 | B7: 44948 | C7: Client-043 | D7: GI Sheets | E7: 1.86 | F7: Edge damage | G7: VS32 | H7: PO-2021-1297 | I7: 1.34 | J7: 118819.77 | K7: =I7*J7 | L7: =IF(INDEX(PO_Facts!$I$2:$I$4801,MATCH(H7,PO_Facts!$A$2:$A$4801,0))<=B7,"yes","FALLBACK: no earlier batch")
A8: RET-0010 | B8: 45237 | C8: Client-007 | D8: MS Flats | E8: 1.38 | F8: Surface rust | G8: VS12 | H8: PO-2023-4221 | I8: 1.38 | J8: 110104.18 | K8: =I8*J8 | L8: =IF(INDEX(PO_Facts!$I$2:$I$4801,MATCH(H8,PO_Facts!$A$2:$A$4801,0))<=B8,"yes","FALLBACK: no earlier batch")
A9: RET-0011 | B9: 44888 | C9: Client-021 | D9: MS Sheets | E9: 3.84 | F9: Surface rust | G9: VS34 | H9: PO-2023-4008 | I9: 3.84 | J9: 82564.52 | K9: =I9*J9 | L9: =IF(INDEX(PO_Facts!$I$2:$I$4801,MATCH(H9,PO_Facts!$A$2:$A$4801,0))<=B9,"yes","FALLBACK: no earlier batch")
A10: RET-0014 | B10: 44524 | C10: Client-067 | D10: SS Sheets | E10: 2.2 | F10: Bend/warp | G10: VS12 | H10: PO-2022-2491 | I10: 2.2 | J10: 120277.26 | K10: =I10*J10 | L10: =IF(INDEX(PO_Facts!$I$2:$I$4801,MATCH(H10,PO_Facts!$A$2:$A$4801,0))<=B10,"yes","FALLBACK: no earlier batch")
A11: RET-0015 | B11: 44805 | C11: Client-058 | D11: GI Pipes | E11: 0.73 | F11: Edge damage | G11: VS12 | H11: PO-2021-1132 | I11: 0.73 | J11: 84695.67 | K11: =I11*J11 | L11: =IF(INDEX(PO_Facts!$I$2:$I$4801,MATCH(H11,PO_Facts!$A$2:$A$4801,0))<=B11,"yes","FALLBACK: no earlier batch")
A12: RET-0016 | B12: 45032 | C12: Client-019 | D12: CR Sheets | E12: 3.96 | F12: Edge damage | G12: VS31 | H12: PO-2022-2525 | I12: 3.96 | J12: 86094.4 | K12: =I12*J12 | L12: =IF(INDEX(PO_Facts!$I$2:$I$4801,MATCH(H12,PO_Facts!$A$2:$A$4801,0))<=B12,"yes","FALLBACK: no earlier batch")
A13: RET-0017 | B13: 44659 | C13: Client-052 | D13: SS Sheets | E13: 2.31 | F13: Edge damage | G13: VS03 | H13: PO-2022-2884 | I13: 2.31 | J13: 80452.99 | K13: =I13*J13 | L13: =IF(INDEX(PO_Facts!$I$2:$I$4801,MATCH(H13,PO_Facts!$A$2:$A$4801,0))<=B13,"yes","FALLBACK: no earlier batch")
... A241: RET-0378 | B241: 44522 | C241: Client-037 | D241: ERW Pipes | E241: 1.28 | F241: Grade mismatch | G241: VS32 | H241: PO-2022-1625 | I241: 1.28 | J241: 55696.69 | K241: =I241*J241 | L241: =IF(INDEX(PO_Facts!$I$2:$I$4801,MATCH(H241,PO_Facts!$A$2:$A$4801,0))<=B241,"yes","FALLBACK: no earlier batch")
A243: Cap rule: a batch cannot return more than (received - rejected) MT in total, so a return is never counted twice against rejection. FALLBACK rows price the return from the supplier's earliest batch of that material because no earlier batch exists.

Sheet Returns_Inferred
A1: return_id | B1: candidate supplier | C1: probability | D1: matched_po (batch) | E1: qty_if_true_MT | F1: batch_price | G1: value if true | H1: EXPECTED VALUE (prob x value)
A2: RET-0000 | B2: VS01 | C2: 0.0198 | D2: PO-2023-4280 | E2: 4.57 | F2: 117934.93 | G2: =E2*F2 | H2: =C2*G2
A3: RET-0000 | B3: VS02 | C3: 0.009 | D3: PO-2023-3787 | E3: 4.57 | F3: 55424.92 | G3: =E3*F3 | H3: =C3*G3
A4: RET-0000 | B4: VS03 | C4: 0.1644 | D4: PO-2021-0229 | E4: 4.57 | F4: 108506.52 | G4: =E4*F4 | H4: =C4*G4
A5: RET-0000 | B5: VS04 | C5: 0.0124 | D5: PO-2021-0166 | E5: 4.57 | F5: 71373.46 | G5: =E5*F5 | H5: =C5*G5
A6: RET-0000 | B6: VS05 | C6: 0.0161 | D6: PO-2022-2511 | E6: 4.57 | F6: 83442.11 | G6: =E6*F6 | H6: =C6*G6
A7: RET-0000 | B7: VS06 | C7: 0.0162 | D7: PO-2021-0994 | E7: 4.57 | F7: 45342.75 | G7: =E7*F7 | H7: =C7*G7
A8: RET-0000 | B8: VS07 | C8: 0.0054 | D8: PO-2022-2089 | E8: 4.57 | F8: 60771.89 | G8: =E8*F8 | H8: =C8*G8
A9: RET-0000 | B9: VS08 | C9: 0.0164 | D9: PO-2021-1060 | E9: 4.57 | F9: 81891.49 | G9: =E9*F9 | H9: =C9*G9
A10: RET-0000 | B10: VS09 | C10: 0.0126 | D10: PO-2023-4224 | E10: 4.57 | F10: 69824.55 | G10: =E10*F10 | H10: =C10*G10
A11: RET-0000 | B11: VS10 | C11: 0.0197 | D11: PO-2023-3857 | E11: 4.57 | F11: 45504.57 | G11: =E11*F11 | H11: =C11*G11
A12: RET-0000 | B12: VS11 | C12: 0.0231 | D12: PO-2021-1370 | E12: 4.57 | F12: 82685.63 | G12: =E12*F12 | H12: =C12*G12
A13: RET-0000 | B13: VS12 | C13: 0.2284 | D13: PO-2022-1818 | E13: 2.284 | F13: 74074.06 | G13: =E13*F13 | H13: =C13*G13
... A4761: RET-0379 | B4761: VS34 | C4761: 0.0065 | D4761: PO-2021-0569 | E4761: 0.79 | F4761: 110313.69 | G4761: =E4761*F4761 | H4761: =C4761*G4761

Sheet Returns_Attributed
A1: return_id | B1: return_date | C1: client_id | D1: material_id | E1: quantity_returned | F1: reason | G1: top1_supplier | H1: top1_prob | I1: top2_supplier | J1: top2_prob | K1: top3_supplier | L1: top3_prob | M1: prob_high_return_group | N1: supplier_level_tier | O1: group_level_call | P1: group_level_confidence
A2: RET-0000 | B2: 2023-11-02 | C2: Client-000 | D2: SS Sheets | E2: 4.57 | F2: Weight short | G2: VS12 | H2: 0.228 | I2: VS19 | J2: 0.172 | K2: VS03 | L2: 0.164 | M2: 0.565 | N2: Medium | O2: High-return-rate group | P2: Weak
A3: RET-0001 | B3: 2021-10-25 | C3: Client-058 | D3: MS Flats | E3: 3.46 | F3: Wrong dimensions | G3: VS12 | H3: 0.1 | I3: VS19 | J3: 0.076 | K3: VS03 | L3: 0.072 | M3: 0.248 | N3: Low | O3: Other suppliers | P3: Strong
A4: RET-0004 | B4: 2021-06-14 | C4: Client-027 | D4: ERW Pipes | E4: 3.38 | F4: Weight short | G4: VS12 | H4: 0.111 | I4: VS19 | J4: 0.084 | K4: VS03 | L4: 0.08 | M4: 0.275 | N4: Low | O4: Other suppliers | P4: Moderate
A5: RET-0006 | B5: 2023-06-11 | C5: Client-039 | D5: CR Sheets | E5: 3.84 | F5: Bend/warp | G5: VS12 | H5: 0.138 | I5: VS19 | J5: 0.104 | K5: VS03 | L5: 0.099 | M5: 0.342 | N5: Low | O5: Other suppliers | P5: Moderate
A6: RET-0012 | B6: 2021-08-21 | C6: Client-029 | D6: MS Rods | E6: 0.2 | F6: Edge damage | G6: VS12 | H6: 0.237 | I6: VS19 | J6: 0.179 | K6: VS03 | L6: 0.171 | M6: 0.587 | N6: Medium | O6: High-return-rate group | P6: Weak
A7: RET-0013 | B7: 2021-11-01 | C7: Client-037 | D7: Structural Steel | E7: 3.25 | F7: Weight short | G7: VS12 | H7: 0.199 | I7: VS19 | J7: 0.15 | K7: VS03 | L7: 0.143 | M7: 0.492 | N7: Low | O7: Other suppliers | P7: Weak
A8: RET-0020 | B8: 2023-06-17 | C8: Client-006 | D8: Angles & Channels | E8: 4.84 | F8: Wrong dimensions | G8: VS12 | H8: 0.311 | I8: VS19 | J8: 0.235 | K8: VS03 | L8: 0.224 | M8: 0.77 | N8: Medium | O8: High-return-rate group | P8: Strong
A9: RET-0021 | B9: 2021-06-26 | C9: Client-060 | D9: MS Pipes | E9: 2.86 | F9: Grade mismatch | G9: VS12 | H9: 0.183 | I9: VS19 | J9: 0.138 | K9: VS03 | L9: 0.132 | M9: 0.452 | N9: Low | O9: Other suppliers | P9: Weak
A10: RET-0024 | B10: 2023-12-19 | C10: Client-027 | D10: MS Pipes | E10: 0.45 | F10: Edge damage | G10: VS12 | H10: 0.275 | I10: VS19 | J10: 0.207 | K10: VS03 | L10: 0.198 | M10: 0.68 | N10: Medium | O10: High-return-rate group | P10: Moderate
A11: RET-0026 | B11: 2022-11-29 | C11: Client-015 | D11: MS Pipes | E11: 0.86 | F11: Wrong dimensions | G11: VS12 | H11: 0.275 | I11: VS19 | J11: 0.207 | K11: VS03 | L11: 0.198 | M11: 0.68 | N11: Medium | O11: High-return-rate group | P11: Moderate
A12: RET-0030 | B12: 2021-03-12 | C12: Client-027 | D12: MS Rods | E12: 1.01 | F12: Bend/warp | G12: VS12 | H12: 0.165 | I12: VS19 | J12: 0.124 | K12: VS03 | L12: 0.119 | M12: 0.408 | N12: Low | O12: Other suppliers | P12: Weak
A13: RET-0033 | B13: 2022-06-09 | C13: Client-063 | D13: Fasteners & Fittings | E13: 2.52 | F13: Weight short | G13: VS12 | H13: 0.23 | I13: VS19 | J13: 0.174 | K13: VS03 | L13: 0.166 | M13: 0.569 | N13: Medium | O13: High-return-rate group | P13: Weak
... A141: RET-0379 | B141: 2023-11-20 | C141: Client-025 | D141: SS Sheets | E141: 0.79 | F141: Grade mismatch | G141: VS12 | H141: 0.333 | I141: VS19 | J141: 0.251 | K141: VS03 | L141: 0.24 | M141: 0.824 | N141: Medium | O141: High-return-rate group | P141: Strong

Sheet Category_Scorecard
A1: supplier_id | B1: in_master | C1: material_id | D1: po_count | E1: short_pct | F1: billing_gap_inr | G1: excess_gap_inr | H1: rejection_loss_inr | I1: avg_days_late | J1: low_sample_flag
A2: VS01 | B2: FALSE | C2: Angles & Channels | D2: 8 | E2: 0.72 | F2: 144307.99 | G2: 45170.13 | H2: 0 | I2: 1.88 | J2: FALSE
A3: VS01 | B3: FALSE | C3: Fasteners & Fittings | D3: 5 | E3: 0.46 | F3: 61154.3 | G3: -3437.94 | H3: 0 | I3: 1.8 | J3: FALSE
A4: VS01 | B4: FALSE | C4: GI Pipes | D4: 11 | E4: 0.37 | F4: 71319 | G4: -30615.63 | H4: 0 | I4: 1.27 | J4: FALSE
A5: VS01 | B5: FALSE | C5: GI Sheets | D5: 7 | E5: 0.52 | F5: 82624.05 | G5: 2665.36 | H5: 0 | I5: 0.86 | J5: FALSE
A6: VS01 | B6: FALSE | C6: GI Wire | D6: 9 | E6: 0.61 | F6: 85596.16 | G6: 11240.36 | H6: 0 | I6: 1.22 | J6: FALSE
A7: VS01 | B7: FALSE | C7: HR Coils | D7: 6 | E7: 0.4 | F7: 43440.17 | G7: -17164.52 | H7: 0 | I7: 2.17 | J7: FALSE
A8: VS01 | B8: FALSE | C8: Hex Bars | D8: 6 | E8: 0.44 | F8: 86108.02 | G8: -9363.65 | H8: 0 | I8: 1.67 | J8: FALSE
A9: VS01 | B9: FALSE | C9: MS Flats | D9: 7 | E9: 0.37 | F9: 41893.18 | G9: -13092.08 | H9: 0 | I9: 1.29 | J9: FALSE
A10: VS01 | B10: FALSE | C10: MS Rods | D10: 6 | E10: 0.3 | F10: 21209.17 | G10: -12884.67 | H10: 0 | I10: 0.83 | J10: FALSE
A11: VS01 | B11: FALSE | C11: MS Sheets | D11: 10 | E11: 0.58 | F11: 108726.98 | G11: 5451.32 | H11: 0 | I11: 1.4 | J11: FALSE
A12: VS01 | B12: FALSE | C12: SS Pipes | D12: 4 | E12: 0.59 | F12: 23960.99 | G12: -1979.24 | H12: 0 | I12: 1.25 | J12: TRUE
A13: VS01 | B13: FALSE | C13: SS Sheets | D13: 10 | E13: 0.48 | F13: 111287.42 | G13: -5662.39 | H13: 0 | I13: 2.1 | J13: FALSE
... A613: VS34 | B613: TRUE | C613: GI Wire | D613: 9 | E613: 0.55 | F613: 122670 | G613: 14186.09 | H613: 0 | I613: 1.89 | J613: FALSE

Sheet Validation
A1: method | B1: top1_acc | C1: top3_acc | D1: logloss
A2: A rate x volume only (no material/date/qty) | B2: 0.225 | C2: 0.558 | D2: 2.917
A3: B + material | B3: 0.224 | C3: 0.55 | D3: 2.904
A4: C + quantity band | B4: 0.225 | C4: 0.558 | D4: 2.906
A5: D + material + quantity [CHOSEN MODEL] | B5: 0.222 | C5: 0.552 | D5: 2.885
A6: E D + date proximity (W60/tau30) | B6: 0.126 | C6: 0.268 | D6: 3.804
A7: F D + date proximity (W90/tau90) | B7: 0.126 | C7: 0.322 | D7: 3.647
A8: G D + date proximity (W180/tau90) | B8: 0.132 | C8: 0.388 | D8: 3.412
A9: Baseline: random among suppliers with a batch in 90d | B9: 0.027 | C9: 0.121 | D9: 16.469
A10: Baseline: latest receipt wins | B10: 0.04 | C10: 0.217
A12: Attribution validated with 5 repeats of 5-fold cross-validation on the 240 known returns; rate/likelihoods re-learned inside each training fold.
A13: Date proximity test: true supplier's latest batch median 84 days before return vs 79 days for other suppliers (Mann-Whitney p = 0.83): no information, so excluded.
A14: Exact-supplier accuracy is modest (top-1 22%) because the three high-return suppliers are near-identical on available features; aggregate return counts per supplier are recovered closely (e.g. VS12 ~51 expected vs 54 actual).
A15: Rupee totals use summed probabilities, which is why they are far more reliable than any single assignment. See the p10-p90 range on Supplier_Impact.

Sheet Sensitivity
A1: scheme | B1: supplier_id | C1: supplier_name | D1: composite | E1: rank | F1: tier
A2: Baseline (35/25/15/15/10) | B2: VS12 | C2: Nutan Tubes | D2: 9.25 | E2: 1 | F2: POOR
A3: Baseline (35/25/15/15/10) | B3: VS19 | C3: Thakur Steel | D3: 9.27 | E3: 2 | F3: POOR
A4: Baseline (35/25/15/15/10) | B4: VS03 | C4: Tata Steel Service | D4: 10.78 | E4: 3 | F4: POOR
A5: Baseline (35/25/15/15/10) | B5: VS17 | C5: Modern Metals | D5: 98.82 | E5: 21 | F5: ACCEPTABLE
A6: Baseline (35/25/15/15/10) | B6: VS16 | C6: Garg Enterprises | D6: 91.24 | E6: 4 | F6: ACCEPTABLE
A7: Baseline (35/25/15/15/10) | B7: VS11 | C7: Sai Steel | D7: 96.97 | E7: 11 | F7: ACCEPTABLE
A8: Baseline (35/25/15/15/10) | B8: VS32 | C8: Precision Steel | D8: 99.1 | E8: 23 | F8: ACCEPTABLE
A9: Baseline (35/25/15/15/10) | B9: VS01 | C9: Jindal Steel & Power | D9: 99.55 | E9: 25 | F9: ACCEPTABLE
A10: Baseline (35/25/15/15/10) | B10: VS05 | C10: Bhushan Steel | D10: 99.24 | E10: 24 | F10: ACCEPTABLE
A11: Baseline (35/25/15/15/10) | B11: VS28 | C11: Param Industries | D11: 97.8 | E11: 14 | F11: ACCEPTABLE
A12: Baseline (35/25/15/15/10) | B12: VS04 | C12: Shyam Metalics | D12: 99.66 | E12: 27 | F12: ACCEPTABLE
A13: Baseline (35/25/15/15/10) | B13: VS08 | C13: Ratnamani Metals | D13: 100 | E13: 32 | F13: ACCEPTABLE
... A137: Equal (20/20/20/20/20) | B137: VS22 | C137: Ratan Steel | D137: 98.93 | E137: 22 | F137: ACCEPTABLE

Sheet Data_Quality_Log
A1: check | B1: result | C1: detail
A2: purchase_orders.po_id unique | B2: PASS | C2: 0 duplicates
A3: goods_receipts.gr_id unique | B3: PASS | C3: 0 duplicates
A4: goods_receipts.po_id unique | B4: PASS | C4: 0 duplicates
A5: payment_records.po_id unique | B5: PASS | C5: 0 duplicates
A6: customer_returns.return_id unique | B6: PASS | C6: 0 duplicates
A7: supplier_master.supplier_id unique | B7: PASS | C7: 0 duplicates
A8: purchase_orders no exact duplicate rows | B8: PASS
A9: goods_receipts no exact duplicate rows | B9: PASS
A10: payment_records no exact duplicate rows | B10: PASS
A11: market_price_index no exact duplicate rows | B11: PASS
A12: supplier_master no exact duplicate rows | B12: PASS
A13: PO -> receipt 1:1 | B13: PASS
A14: PO -> payment 1:1 | B14: PASS
A15: all PO suppliers in master | B15: PASS
A16: all units are MT | B16: PASS | C16: {'MT': 4800}
A17: supplier_id agrees PO vs payment | B17: PASS
A18: payment terms agree PO vs payment | B18: PASS
A19: receipt_date >= po_date | B19: PASS
A20: promised date >= po_date | B20: PASS
A21: received <= ordered | B21: PASS
A22: rejection_qty <= received | B22: PASS
A23: rejection_qty >=0 and days_late >=0 | B23: PASS
A24: invoice = ordered qty x quoted price (within 0.01%) | B24: PASS | C24: ratio min 1.000000 max 1.000000
A25: rejection rows all have a reason | B25: PASS | C25: 424 rows with rejection_qty>0; 424 rows with a reason (not identical sets)
A26: paid-after-invoice check: actual_payment_date >= invoice_date | B26: PASS
A27: returns: dates inside PO window | B27: PASS
A28: returns: material exists in POs | B28: PASS
A29: returns: traced supplier in master | B29: PASS
A30: returns: missing supplier share (info) | B30: PASS | C30: 140 of 380 = 36.8% -> inference required
A31: PO materials inside supplier_master categories (info) | B31: PASS | C31: 621 in-master POs, 4179 off-master (87.1%) -> tagged, not dropped
A32: market index coverage (info) | B32: PASS | C32: 1611 of 4800 POs (33.6%) matched; materials: ['ERW Pipes', 'GI Pipes', 'HR Coils', 'MS Pipes', 'MS Sheets', 'SS Pipes']
A33: market index level vs PO prices (info) | B33: PASS | C33: median PO price is +14% vs index on covered POs -> level gap, use panel comparison as primary
A34: panel baseline short % (median supplier) | B34: PASS | C34: 0.511%
